LICENSE
MANIFEST.in
README.rst
setup.cfg
setup.py
artellapipe/__init__.py
artellapipe/dccs/__init__.py
artellapipe/dccs/houdini/__init__.py
artellapipe/dccs/houdini/__logging__.ini
artellapipe/dccs/houdini/__version__.py
artellapipe/dccs/houdini/core/__init__.py
artellapipe/dccs/houdini/core/toolbox.py
artellapipe/dccs/houdini/managers/__init__.py
artellapipe/dccs/houdini/managers/shelf.py
artellapipe_dccs_houdini.egg-info/PKG-INFO
artellapipe_dccs_houdini.egg-info/SOURCES.txt
artellapipe_dccs_houdini.egg-info/dependency_links.txt
artellapipe_dccs_houdini.egg-info/not-zip-safe
artellapipe_dccs_houdini.egg-info/requires.txt
artellapipe_dccs_houdini.egg-info/top_level.txt
tests/__init__.py
tests/test_general.py