Metadata-Version: 2.1
Name: artellapipe-dccs-houdini
Version: 0.0.3
Summary: Houdini libraries for ArtellaPipe
Home-page: https://github.com/ArtellaPipe/artellapipe-dccs-houdini
Author: Tomas Poveda
Author-email: tpovedatd@gmail.com
License: MIT
Platform: UNKNOWN
Provides-Extra: test
Provides-Extra: dev
